text_prettifier/__init__.py
text_prettifier/_version.py
text_prettifier/text_prettifier.py
text_prettifier/version.py
text_prettifier/utils/__init__.py
text_prettifier/utils/patterns.py
text_prettifier-2.0.1.dist-info/licenses/LICENSE
text_prettifier-2.0.1.dist-info/METADATA
text_prettifier-2.0.1.dist-info/WHEEL
text_prettifier-2.0.1.dist-info/top_level.txt
text_prettifier-2.0.1.dist-info/RECORD
