Metadata-Version: 2.4
Name: text-prettifier
Version: 2.0.1
Summary: A Python library for cleaning and preprocessing text data with asynchronous and multithreading capabilities.
Author: Qadeer Ahmad
Author-email: mrqadeer1231122@gmail.com
Keywords: text cleaning,text preprocessing,text scrubber,NLP,natural language processing,data cleaning,data preprocessing,string manipulation,text manipulation,stopwords removal,contractions expansion,text normalization,text sanitization,internet words removal,emojis removal,emojis killer,asynchronous,async,multithreading,parallel processing,batch processing
Classifier: Development Status :: 4 - Beta
Classifier: Intended Audience :: Developers
Classifier: Programming Language :: Python :: 3
Classifier: Programming Language :: Python :: 3.6
Classifier: Programming Language :: Python :: 3.7
Classifier: Programming Language :: Python :: 3.8
Classifier: Programming Language :: Python :: 3.9
Classifier: Programming Language :: Python :: 3.10
Classifier: Programming Language :: Python :: 3.11
Classifier: Operating System :: Unix
Classifier: Operating System :: MacOS :: MacOS X
Classifier: Operating System :: Microsoft :: Windows
Classifier: Topic :: Text Processing
Classifier: Topic :: Text Processing :: Linguistic
Classifier: License :: OSI Approved :: MIT License
Requires-Python: >=3.6
License-File: LICENSE
Requires-Dist: contractions
Requires-Dist: nltk
Requires-Dist: internet-words-remover
Requires-Dist: typing; python_version < "3.8"
Dynamic: author
Dynamic: author-email
Dynamic: classifier
Dynamic: description
Dynamic: description-content-type
Dynamic: keywords
Dynamic: license-file
Dynamic: requires-dist
Dynamic: requires-python
Dynamic: summary
